{
  "name": "acf/pricing-panel",
  "title": "Pricing Panel",
  "description": "A heading with 2 or 3 pricing cards — price, feature list, and a button per plan",
  "category": "theme",
  "icon": "<svg width='24px' height='24px' viewBox='0 0 24 24' fill='none' xmlns='http://www.w3.org/2000/svg'><rect x='4' y='4' width='6' height='16' rx='1' stroke='#000' stroke-width='2'/><rect x='13' y='4' width='7' height='16' rx='1' stroke='#000' stroke-width='2'/><path d='M15.5 9h2M15.5 12h2' stroke='#000' stroke-width='2' stroke-linecap='round'/></svg>",
  "keywords": ["pricing", "plans", "cards", "vans", "prices"],
  "acf": {
    "mode": "edit",
    "renderTemplate": "pricing-panel.php"
  },
  "supports": {
    "anchor": true,
    "html": false,
    "align": false
  }
}
